{
  "timestamp_end": 17.4,
  "section": "Section 2: Why it looked so bad (clip)",
  "content_type": "game",
  "duration": 4.0,
  "channel_name": "Global Flash 24",
  "timestamp_start": 13.4,
  "source_url": "https://www.youtube.com/watch?v=XBxpYfq8lxg",
  "downloaded_at": "2026-05-29T06:41:35.474780+00:00",
  "visual_break_after": true,
  "video_title": "Ryan Lindgren EJECTED After Brutal Hit on Evan Bouchard \ud83d\ude31 | IIHF 2026 Hockey Drama",
  "topic": "2026 05 29 evan bouchard knocked out by dirty hit at worlds"
}